gisutils/__init__.py
gisutils/_version.py
gisutils/projection.py
gisutils/raster.py
gisutils/shapefile.py
gisutils/utils.py
gisutils/tests/__init__.py
gisutils/tests/conftest.py
gisutils/tests/test_examples.py
gisutils/tests/test_notebooks.py
gisutils/tests/test_projection.py
gisutils/tests/test_raster.py
gisutils/tests/test_shapefile.py
gis_utils-0.3.6.dist-info/AUTHORS.rst
gis_utils-0.3.6.dist-info/LICENSE
gis_utils-0.3.6.dist-info/METADATA
gis_utils-0.3.6.dist-info/WHEEL
gis_utils-0.3.6.dist-info/top_level.txt
gis_utils-0.3.6.dist-info/RECORD
