Metadata-Version: 2.1
Name: gis-utils
Version: 0.3.6
Summary: Convenience functions for working with geospatial data in python. 
Author-email: Andrew Leaf <aleaf@usgs.gov>
Project-URL: documentation, https://aleaf.github.io/gis-utils/latest/
Project-URL: repository, https://github.com/aleaf/gis-utils
Keywords: GIS,python,hydrology
Classifier: Development Status :: 4 - Beta
Classifier: Intended Audience :: Science/Research
Classifier: Programming Language :: Python :: 3 :: Only
Classifier: Topic :: Scientific/Engineering :: Hydrology
Requires-Python: >=3.10
License-File: LICENSE
License-File: AUTHORS.rst
Requires-Dist: geopandas
Requires-Dist: fiona
Requires-Dist: matplotlib
Requires-Dist: numpy
Requires-Dist: pandas
Requires-Dist: pyproj
Requires-Dist: rasterio
Requires-Dist: scipy
Requires-Dist: shapely
Requires-Dist: xarray
Provides-Extra: docs
Requires-Dist: matplotlib; extra == "docs"
Requires-Dist: ipython[kernel]; extra == "docs"
Requires-Dist: sphinx; extra == "docs"
Requires-Dist: numpydoc; extra == "docs"
Requires-Dist: nbsphinx; extra == "docs"
Requires-Dist: sphinx-copybutton; extra == "docs"
Requires-Dist: sphinx-rtd-theme; extra == "docs"
Provides-Extra: optional
Provides-Extra: test
Requires-Dist: codecov; extra == "test"
Requires-Dist: coverage; extra == "test"
Requires-Dist: pytest; extra == "test"
Requires-Dist: pytest-timeout; extra == "test"
